{
    "project": {
        "name": "pickadate",
        "title": "pickadate.js",
        "description": "The mobile-friendly, responsive, and lightweight jQuery date & time input picker.",
        "version": "4.0.0-0",
        "url": "http://amsul.github.io/pickadate.js",
        "repo": "https://github.com/amsul/pickadate.js"
    },
    "files": {
        "lib/ui-pickadate.js": {
            "name": "lib/ui-pickadate.js",
            "modules": {},
            "classes": {
                "shadow.Pickadate": 1
            },
            "fors": {},
            "namespaces": {}
        },
        "lib/ui-picker.js": {
            "name": "lib/ui-picker.js",
            "modules": {},
            "classes": {
                "shadow.Picker": 1
            },
            "fors": {},
            "namespaces": {}
        }
    },
    "modules": {},
    "classes": {
        "shadow.Pickadate": {
            "name": "shadow.Pickadate",
            "shortname": "shadow.Pickadate",
            "classitems": [],
            "plugins": [],
            "extensions": [],
            "plugin_for": [],
            "extension_for": [],
            "file": "lib/ui-pickadate.js",
            "line": 19,
            "description": "Construct a pickadate shadow object.",
            "static": 1,
            "extends": "shadow.Picker"
        },
        "shadow.Picker": {
            "name": "shadow.Picker",
            "shortname": "shadow.Picker",
            "classitems": [],
            "plugins": [],
            "extensions": [],
            "plugin_for": [],
            "extension_for": [],
            "file": "lib/ui-picker.js",
            "line": 17,
            "description": "Construct a picker shadow object.",
            "static": 1,
            "extends": "shadow.DataElement"
        }
    },
    "classitems": [
        {
            "file": "lib/ui-pickadate.js",
            "line": 32,
            "description": "The min range.",
            "itemtype": "attribute",
            "name": "attrs.min",
            "type": "Array|Date|String|Number|shadow.Date",
            "default": "null",
            "class": "shadow.Pickadate"
        },
        {
            "file": "lib/ui-pickadate.js",
            "line": 42,
            "description": "The max range.",
            "itemtype": "attribute",
            "name": "attrs.max",
            "type": "Array|Date|String|Number|shadow.Date",
            "default": "null",
            "class": "shadow.Pickadate"
        },
        {
            "file": "lib/ui-pickadate.js",
            "line": 52,
            "description": "The date today.",
            "access": "protected",
            "tagname": "",
            "itemtype": "attribute",
            "name": "attrs.today",
            "type": "shadow.Date",
            "default": "null",
            "class": "shadow.Pickadate"
        },
        {
            "file": "lib/ui-pickadate.js",
            "line": 63,
            "description": "The 1st date of the month in view.",
            "access": "private",
            "tagname": "",
            "itemtype": "attribute",
            "name": "attrs.view",
            "type": "shadow.Date",
            "default": "null",
            "class": "shadow.Pickadate"
        },
        {
            "file": "lib/ui-pickadate.js",
            "line": 74,
            "description": "The highlighted date that acts as a visual cue of focus.",
            "itemtype": "attribute",
            "name": "attrs.highlight",
            "type": "Array|Date|String|Number|shadow.Date",
            "default": "null",
            "class": "shadow.Pickadate"
        },
        {
            "file": "lib/ui-pickadate.js",
            "line": 84,
            "description": "The selected date that mirrors the value.",
            "itemtype": "attribute",
            "name": "attrs.select",
            "type": "Array|Date|String|Number|shadow.Date",
            "default": "null",
            "class": "shadow.Pickadate"
        },
        {
            "file": "lib/ui-pickadate.js",
            "line": 94,
            "description": "The default formatting to use.",
            "itemtype": "attribute",
            "name": "attrs.format",
            "type": "String",
            "default": "'d mmmm, yyyy'",
            "class": "shadow.Pickadate"
        },
        {
            "file": "lib/ui-pickadate.js",
            "line": 104,
            "description": "The first day of the week. Truth-y sets to Monday.",
            "itemtype": "attribute",
            "name": "attrs.firstDay",
            "type": "Number",
            "default": "null",
            "class": "shadow.Pickadate"
        },
        {
            "file": "lib/ui-pickadate.js",
            "line": 114,
            "description": "Show either the years, months, or dates grid.",
            "itemtype": "attribute",
            "name": "attrs.show",
            "type": "String",
            "default": "null",
            "class": "shadow.Pickadate"
        },
        {
            "file": "lib/ui-pickadate.js",
            "line": 127,
            "description": "Today label.",
            "itemtype": "attribute",
            "name": "dict.today",
            "type": "String",
            "default": "'Today'",
            "class": "shadow.Pickadate"
        },
        {
            "file": "lib/ui-pickadate.js",
            "line": 137,
            "description": "Clear label.",
            "itemtype": "attribute",
            "name": "dict.clear",
            "type": "String",
            "default": "'Clear'",
            "class": "shadow.Pickadate"
        },
        {
            "file": "lib/ui-pickadate.js",
            "line": 147,
            "description": "The list of full months.",
            "itemtype": "attribute",
            "name": "dict.monthsFull",
            "type": "Array",
            "default": "['January', 'February', ...]",
            "class": "shadow.Pickadate"
        },
        {
            "file": "lib/ui-pickadate.js",
            "line": 158,
            "description": "The list of short months.",
            "itemtype": "attribute",
            "name": "dict.monthsShort",
            "type": "Array",
            "default": "['Jan', 'Feb', ...]",
            "class": "shadow.Pickadate"
        },
        {
            "file": "lib/ui-pickadate.js",
            "line": 169,
            "description": "The list of full weekdays.",
            "itemtype": "attribute",
            "name": "dict.weekdaysFull",
            "type": "Array",
            "default": "['Sunday', 'Monday', ...]",
            "class": "shadow.Pickadate"
        },
        {
            "file": "lib/ui-pickadate.js",
            "line": 180,
            "description": "The list of short weekdays.",
            "itemtype": "attribute",
            "name": "dict.weekdaysShort",
            "type": "Array",
            "default": "['Sun', 'Mon', ...]",
            "class": "shadow.Pickadate"
        },
        {
            "file": "lib/ui-pickadate.js",
            "line": 287,
            "itemtype": "method",
            "name": "setup",
            "class": "shadow.Pickadate"
        },
        {
            "file": "lib/ui-pickadate.js",
            "line": 393,
            "description": "Create an instance of a pickadate object.",
            "static": 1,
            "itemtype": "method",
            "name": "create",
            "params": [
                {
                    "name": "options",
                    "description": "Options for the element’s prototype.",
                    "type": "Object"
                }
            ],
            "return": {
                "description": "An instance of the pickadate element.",
                "type": "shadow.Pickadate"
            },
            "class": "shadow.Pickadate"
        },
        {
            "file": "lib/ui-pickadate.js",
            "line": 468,
            "description": "Add a unit to a named attribute collection.",
            "class": "shadow.Pickadate"
        },
        {
            "file": "lib/ui-pickadate.js",
            "line": 478,
            "description": "Remove a unit from a named attribute collection.",
            "class": "shadow.Pickadate"
        },
        {
            "file": "lib/ui-pickadate.js",
            "line": 488,
            "description": "Parse a date into it’s attribute format.",
            "class": "shadow.Pickadate"
        },
        {
            "file": "lib/ui-pickadate.js",
            "line": 538,
            "description": "Get a new selection by passing a date.\nAn optional shadow date can be passed as a “hook” for a range.\nAn optional boolean can be passed to wrap the date into an array.",
            "class": "shadow.Pickadate"
        },
        {
            "file": "lib/ui-pickadate.js",
            "line": 560,
            "description": "Get a new range selection by passing a date.\nAn optional shadow date can be passed as a “hook” for a range.",
            "class": "shadow.Pickadate"
        },
        {
            "file": "lib/ui-pickadate.js",
            "line": 581,
            "description": "Get a new mutiple selection by passing a date.\nAn optional shadow date can be passed as a “hook” for a range.",
            "class": "shadow.Pickadate"
        },
        {
            "file": "lib/ui-pickadate.js",
            "line": 619,
            "description": "Get a new date assignment to use for attributes.",
            "class": "shadow.Pickadate"
        },
        {
            "file": "lib/ui-pickadate.js",
            "line": 639,
            "description": "Get a new range date assignment to use for attributes.",
            "class": "shadow.Pickadate"
        },
        {
            "file": "lib/ui-pickadate.js",
            "line": 660,
            "description": "Get a new multiple date assignment to use for attributes.",
            "class": "shadow.Pickadate"
        },
        {
            "file": "lib/ui-pickadate.js",
            "line": 682,
            "description": "Clone a selection into shadow dates.",
            "class": "shadow.Pickadate"
        },
        {
            "file": "lib/ui-pickadate.js",
            "line": 700,
            "description": "Clone the last date in a selection.",
            "class": "shadow.Pickadate"
        },
        {
            "file": "lib/ui-pickadate.js",
            "line": 718,
            "description": "Checks if a date is disabled and then returns the next enabled one.",
            "class": "shadow.Pickadate"
        },
        {
            "file": "lib/ui-pickadate.js",
            "line": 762,
            "description": "Check if a date is selected.\nOptionally, a “comparison” can be passed to scope the comparison.",
            "class": "shadow.Pickadate"
        },
        {
            "file": "lib/ui-pickadate.js",
            "line": 1324,
            "description": "Build out the templating for the pickadate.",
            "class": "shadow.Pickadate"
        },
        {
            "file": "lib/ui-pickadate.js",
            "line": 1344,
            "description": "Add a leading zero for numbers below 9.",
            "class": "shadow.Pickadate"
        },
        {
            "file": "lib/ui-picker.js",
            "line": 43,
            "description": "Create a picker object.",
            "class": "shadow.Picker"
        },
        {
            "file": "lib/ui-picker.js",
            "line": 85,
            "description": "Build out the templating for the picker.",
            "class": "shadow.Picker"
        },
        {
            "file": "lib/ui-picker.js",
            "line": 109,
            "description": "Open & close the picker.",
            "class": "shadow.Picker"
        },
        {
            "file": "lib/ui-picker.js",
            "line": 125,
            "description": "When the document is clicked, close the picker.",
            "class": "shadow.Picker"
        }
    ],
    "warnings": [
        {
            "message": "Missing item type\nAdd a unit to a named attribute collection.",
            "line": " lib/ui-pickadate.js:468"
        },
        {
            "message": "Missing item type\nRemove a unit from a named attribute collection.",
            "line": " lib/ui-pickadate.js:478"
        },
        {
            "message": "Missing item type\nParse a date into it’s attribute format.",
            "line": " lib/ui-pickadate.js:488"
        },
        {
            "message": "Missing item type\nGet a new selection by passing a date.\nAn optional shadow date can be passed as a “hook” for a range.\nAn optional boolean can be passed to wrap the date into an array.",
            "line": " lib/ui-pickadate.js:538"
        },
        {
            "message": "Missing item type\nGet a new range selection by passing a date.\nAn optional shadow date can be passed as a “hook” for a range.",
            "line": " lib/ui-pickadate.js:560"
        },
        {
            "message": "Missing item type\nGet a new mutiple selection by passing a date.\nAn optional shadow date can be passed as a “hook” for a range.",
            "line": " lib/ui-pickadate.js:581"
        },
        {
            "message": "Missing item type\nGet a new date assignment to use for attributes.",
            "line": " lib/ui-pickadate.js:619"
        },
        {
            "message": "Missing item type\nGet a new range date assignment to use for attributes.",
            "line": " lib/ui-pickadate.js:639"
        },
        {
            "message": "Missing item type\nGet a new multiple date assignment to use for attributes.",
            "line": " lib/ui-pickadate.js:660"
        },
        {
            "message": "Missing item type\nClone a selection into shadow dates.",
            "line": " lib/ui-pickadate.js:682"
        },
        {
            "message": "Missing item type\nClone the last date in a selection.",
            "line": " lib/ui-pickadate.js:700"
        },
        {
            "message": "Missing item type\nChecks if a date is disabled and then returns the next enabled one.",
            "line": " lib/ui-pickadate.js:718"
        },
        {
            "message": "Missing item type\nCheck if a date is selected.\nOptionally, a “comparison” can be passed to scope the comparison.",
            "line": " lib/ui-pickadate.js:762"
        },
        {
            "message": "Missing item type\nBuild out the templating for the pickadate.",
            "line": " lib/ui-pickadate.js:1324"
        },
        {
            "message": "Missing item type\nAdd a leading zero for numbers below 9.",
            "line": " lib/ui-pickadate.js:1344"
        },
        {
            "message": "Missing item type\nCreate a picker object.",
            "line": " lib/ui-picker.js:43"
        },
        {
            "message": "Missing item type\nBuild out the templating for the picker.",
            "line": " lib/ui-picker.js:85"
        },
        {
            "message": "Missing item type\nOpen & close the picker.",
            "line": " lib/ui-picker.js:109"
        },
        {
            "message": "Missing item type\nWhen the document is clicked, close the picker.",
            "line": " lib/ui-picker.js:125"
        }
    ]
}